tinyaes.cpython-313-darwin.so
tinyaes-1.1.1.dist-info/RECORD
tinyaes-1.1.1.dist-info/WHEEL
tinyaes-1.1.1.dist-info/top_level.txt
tinyaes-1.1.1.dist-info/LICENSE.txt
tinyaes-1.1.1.dist-info/METADATA
