Metadata-Version: 2.1
Name: tinyaes
Version: 1.1.1
Summary: tiny-AES-c wrapper in Cython
Home-page: https://github.com/naufraghi/tinyaes-py
Author: Matteo Bertini
Author-email: naufraghi@develer.com
License: MIT
Keywords: AES Cryptography block-cipher stream-cipher
Classifier: Development Status :: 5 - Production/Stable
Classifier: Intended Audience :: Developers
Classifier: Topic :: Security :: Cryptography
Classifier: License :: OSI Approved :: MIT License
Classifier: Programming Language :: Python :: 3
Classifier: Programming Language :: Cython
License-File: LICENSE.txt
